hyperjet.cpython-37m-x86_64-linux-gnu.so
hyperjet-1.5.0.dist-info/LICENSE
hyperjet-1.5.0.dist-info/top_level.txt
hyperjet-1.5.0.dist-info/RECORD
hyperjet-1.5.0.dist-info/METADATA
hyperjet-1.5.0.dist-info/WHEEL
