Metadata-Version: 2.1
Name: hyperjet
Version: 1.5.0
Summary: Automatic differentiation with dual numbers
Home-page: https://github.com/oberbichler/HyperJet
Author: Thomas Oberbichler
Author-email: thomas.oberbichler@gmail.com
Classifier: Programming Language :: Python :: 3.6
Classifier: Programming Language :: Python :: 3.7
Classifier: Programming Language :: Python :: 3.8
Classifier: Programming Language :: Python :: 3.9
Classifier: License :: OSI Approved :: MIT License
Requires-Python: >=3.6
License-File: LICENSE
Requires-Dist: numpy
Requires-Dist: msvc-runtime ; platform_system == "Windows"
Provides-Extra: test
Requires-Dist: pytest ; extra == 'test'
